exai_client/__init__.py
exai_client-0.0.1.dist-info/METADATA
exai_client-0.0.1.dist-info/WHEEL
exai_client-0.0.1.dist-info/top_level.txt
exai_client-0.0.1.dist-info/RECORD
