Metadata-Version: 2.4
Name: exai-client
Version: 0.0.1
Summary: ExAI Labs - Client package (placeholder)
Author-email: ExAI Labs <contact@exailabs.ai>
License-Expression: MIT
Project-URL: Homepage, https://github.com/exailabs/exai-pypi-placeholders
Project-URL: Repository, https://github.com/exailabs/exai-pypi-placeholders
Project-URL: Issues, https://github.com/exailabs/exai-pypi-placeholders/issues
Keywords: exai,client,api,sdk
Classifier: Development Status :: 1 - Planning
Classifier: Intended Audience :: Developers
Classifier: Programming Language :: Python :: 3
Classifier: Programming Language :: Python :: 3.8
Classifier: Programming Language :: Python :: 3.9
Classifier: Programming Language :: Python :: 3.10
Classifier: Programming Language :: Python :: 3.11
Classifier: Programming Language :: Python :: 3.12
Requires-Python: >=3.8
